rustberry-0.0.14.dist-info/METADATA
rustberry-0.0.14.dist-info/WHEEL
rustberry-0.0.14.dist-info/license_files/LICENSE
rustberry/__init__.py
rustberry/_rustberry.pyi
rustberry/_rustberry.cpython-311-darwin.so
rustberry-0.0.14.dist-info/RECORD
